django_location_maps-1.1.2.dist-info/DESCRIPTION.rst
django_location_maps-1.1.2.dist-info/METADATA
django_location_maps-1.1.2.dist-info/RECORD
django_location_maps-1.1.2.dist-info/WHEEL
django_location_maps-1.1.2.dist-info/metadata.json
django_location_maps-1.1.2.dist-info/top_level.txt
location/__init__.py
location/admin.py
location/apps.py
location/filters.py
location/forms.py
location/inlines.py
location/managers.py
location/models.py
location/serializers.py
location/tests.py
location/urls.py
location/views.py
location/widgets.py
location/api/__init__.py
location/api/filters.py
location/api/urls.py
location/fixtures/initial_data.json
location/migrations/0001_initial.py
location/migrations/0002_auto_20180308_1337.py
location/migrations/0003_auto_20180404_1822.py
location/migrations/0004_auto_20180409_1319.py
location/migrations/0005_auto_20180409_1322.py
location/migrations/0006_auto_20180409_1326.py
location/migrations/0007_auto_20180409_1327.py
location/migrations/0008_auto_20180409_1328.py
location/migrations/0009_auto_20180409_1456.py
location/migrations/0010_auto_20180409_2118.py
location/migrations/0011_auto_20180528_1621.py
location/migrations/__init__.py
location/static/css/custom.css
location/static/css/custom.css.map
location/static/css/custom.scss
location/static/js/custom.js
location/static/js/jquery-1.12.4.js
location/static/js/location.js
location/templates/admin/location/change_form.html
location/templates/admin/location/change_form_location.html
location/templates/admin/location/map.html
location/templates/admin/location/stacked.html
location/templates/admin/location/tabular.html
location/templates/admin/location/filters/custom_select_filter.html
